convenient_formsets/__init__.py
convenient_formsets/apps.py
convenient_formsets/formsets.py
convenient_formsets/py.typed
convenient_formsets/static/convenient_formsets/convenient_formsets.js
convenient_formsets/static/convenient_formsets/convenient_formsets.min.js
django_convenient_formsets-2.0.dist-info/LICENSE
django_convenient_formsets-2.0.dist-info/METADATA
django_convenient_formsets-2.0.dist-info/WHEEL
django_convenient_formsets-2.0.dist-info/top_level.txt
django_convenient_formsets-2.0.dist-info/RECORD
