Metadata-Version: 2.1
Name: django-convenient-formsets
Version: 2.0
Summary: Django dynamic formsets made convenient for users and developers alike.
Home-page: https://github.com/tiesjan/django-convenient-formsets
Author: Ties Jan Hefting
Author-email: hello@tiesjan.com
License: BSD
Project-URL: Bugs, https://github.com/tiesjan/django-convenient-formsets/issues
Project-URL: Changes, https://github.com/tiesjan/django-convenient-formsets/blob/main/CHANGES.md
Classifier: Development Status :: 5 - Production/Stable
Classifier: Environment :: Web Environment
Classifier: Framework :: Django :: 4.2
Classifier: Intended Audience :: Developers
Classifier: License :: OSI Approved :: BSD License
Classifier: Operating System :: OS Independent
Classifier: Programming Language :: Python :: 3.8
Classifier: Programming Language :: Python :: 3.9
Classifier: Programming Language :: Python :: 3.10
Classifier: Programming Language :: Python :: 3.11
Classifier: Topic :: Internet :: WWW/HTTP
Requires-Python: >=3.8
License-File: LICENSE
Requires-Dist: Django (>=4.2)
